tree_climber/__init__.py
tree_climber/__main__.py
tree_climber/ast_creator.py
tree_climber/base_visitor.py
tree_climber/cfg_creator.py
tree_climber/config.py
tree_climber/globals.py
tree_climber/tree_sitter_utils.py
tree_climber/dataflow/__init__.py
tree_climber/dataflow/dataflow_solver.py
tree_climber/dataflow/def_use.py
tree_climber/dataflow/reaching_def.py
tree_climber/export/cpg.py
tree_climber-0.0.1.dist-info/METADATA
tree_climber-0.0.1.dist-info/WHEEL
tree_climber-0.0.1.dist-info/licenses/LICENSE
tree_climber-0.0.1.dist-info/RECORD
