Metadata-Version: 2.1
Name: tree-climber
Version: 0.0.1
Summary: Program analysis tools built on tree-sitter.
Project-URL: Homepage, https://github.com/bstee615/tree-climber
Project-URL: Bug Tracker, https://github.com/bstee615/tree-climber/issues
Author-email: Benjamin Steenhoek <benjaminjsteenhoek@gmail.com>
License: MIT License
License-File: LICENSE
Keywords: cfg,cpg,dfg,pdg,program-analysis,tree-sitter
Classifier: License :: OSI Approved :: MIT License
Classifier: Operating System :: OS Independent
Classifier: Programming Language :: Python :: 3
Requires-Python: >=3.7
Requires-Dist: gitpython
Requires-Dist: matplotlib
Requires-Dist: networkx
Requires-Dist: pygraphviz
Requires-Dist: tree-sitter
